lastfm_auth
