Metadata-Version: 1.0
Name: django-lastfm-auth
Version: 0.2.2
Summary: django-lastfm-auth is an extension to django-social-auth which adds a backend for Last.fm.
Home-page: https://github.com/mlavin/django-lastfm-auth
Author: Mark Lavin
Author-email: markdlavin@gmail.com
License: BSD
Platform: UNKNOWN
Classifier: Topic :: Internet :: WWW/HTTP :: Dynamic Content
Classifier: Intended Audience :: Developers
Classifier: License :: OSI Approved :: BSD License
Classifier: Programming Language :: Python
Classifier: Topic :: Software Development :: Libraries :: Python Modules
Classifier: Development Status :: 4 - Beta
Classifier: Operating System :: OS Independent
